qr2cnc-0.0.2.dist-info/DESCRIPTION.rst
qr2cnc-0.0.2.dist-info/METADATA
qr2cnc-0.0.2.dist-info/RECORD
qr2cnc-0.0.2.dist-info/WHEEL
qr2cnc-0.0.2.dist-info/entry_points.txt
qr2cnc-0.0.2.dist-info/metadata.json
qr2cnc-0.0.2.dist-info/top_level.txt
qrcnc/__init__.py
qrcnc/__main__.py
